LICENSE
MANIFEST.in
README.rst
pavement.py
requirements.txt
setup.py
docs/api.rst
docs/conf.py
docs/gtkwave_id0.png
docs/index.rst
docs/.build/doctrees/api.doctree
docs/.build/doctrees/environment.pickle
docs/.build/doctrees/index.doctree
docs/.build/doctrees/api/modules.doctree
docs/.build/doctrees/api/pysimavr.doctree
docs/.build/doctrees/api/pysimavr.examples.doctree
docs/.build/doctrees/api/pysimavr.swig.doctree
docs/.build/html/.buildinfo
docs/.build/html/api.html
docs/.build/html/genindex.html
docs/.build/html/index.html
docs/.build/html/objects.inv
docs/.build/html/py-modindex.html
docs/.build/html/search.html
docs/.build/html/searchindex.js
docs/.build/html/_images/gtkwave_id0.png
docs/.build/html/_sources/api.txt
docs/.build/html/_sources/index.txt
docs/.build/html/_sources/api/modules.txt
docs/.build/html/_sources/api/pysimavr.examples.txt
docs/.build/html/_sources/api/pysimavr.swig.txt
docs/.build/html/_sources/api/pysimavr.txt
docs/.build/html/_static/ajax-loader.gif
docs/.build/html/_static/basic.css
docs/.build/html/_static/classic.css
docs/.build/html/_static/comment-bright.png
docs/.build/html/_static/comment-close.png
docs/.build/html/_static/comment.png
docs/.build/html/_static/default.css
docs/.build/html/_static/doctools.js
docs/.build/html/_static/down-pressed.png
docs/.build/html/_static/down.png
docs/.build/html/_static/file.png
docs/.build/html/_static/jquery-1.11.1.js
docs/.build/html/_static/jquery.js
docs/.build/html/_static/minus.png
docs/.build/html/_static/plus.png
docs/.build/html/_static/pygments.css
docs/.build/html/_static/searchtools.js
docs/.build/html/_static/sidebar.js
docs/.build/html/_static/underscore-1.3.1.js
docs/.build/html/_static/underscore.js
docs/.build/html/_static/up-pressed.png
docs/.build/html/_static/up.png
docs/.build/html/_static/websupport.js
docs/.build/html/api/modules.html
docs/.build/html/api/pysimavr.examples.html
docs/.build/html/api/pysimavr.html
docs/.build/html/api/pysimavr.swig.html
pysimavr.egg-info/PKG-INFO
pysimavr.egg-info/SOURCES.txt
pysimavr.egg-info/dependency_links.txt
pysimavr.egg-info/not-zip-safe
pysimavr.egg-info/requires.txt
pysimavr.egg-info/top_level.txt
