Metadata-Version: 1.1
Name: pysimavr
Version: 0.2.2
Summary: python wrapper for simavr which is AVR and arduino simulator.
Home-page: https://github.com/ponty/pysimavr
Author: ponty
Author-email: UNKNOWN
License: GPL
Keywords: avr simavr
Platform: UNKNOWN
Classifier: License :: OSI Approved :: BSD License
Classifier: Natural Language :: English
Classifier: Operating System :: OS Independent
Classifier: Programming Language :: Python
Classifier: Programming Language :: Python :: 2
Classifier: Programming Language :: Python :: 2.6
Classifier: Programming Language :: Python :: 2.7
Classifier: Programming Language :: Python :: 3
Classifier: Programming Language :: Python :: 3.3
Classifier: Programming Language :: Python :: 3.4
Classifier: Programming Language :: Python :: 3.5
